pyenvutils/__init__.py
pyenvutils/pyenvutils.py
pyenvutils-1.0.0.3.dist-info/entry_points.txt
pyenvutils-1.0.0.3.dist-info/WHEEL
pyenvutils-1.0.0.3.dist-info/METADATA
pyenvutils-1.0.0.3.dist-info/RECORD
