Metadata-Version: 2.1
Name: pyenvutils
Version: 1.0.0.3
Summary: Python environment directory utilities
Home-page: https://github.com/dougransom/pyenvutils
Keywords: python,directories,sys,site,shell,environment
Author: Doug Ransom
Author-email: doug@ransom.vip
Requires-Python: >=3.3
Classifier: Intended Audience :: Developers
Classifier: Programming Language :: Python :: 3
Classifier: Topic :: Software Development :: Libraries :: Python Modules
Classifier: Development Status :: 5 - Production/Stable
